[{"event_date":"2022-02-03","event_type":"hull_cleaning","cost_usd":93895.6784,"downtime_hours":35.8062,"me_recovery_pct":96.8937,"payback_days":7.9352},{"event_date":"2022-02-22","event_type":"propeller_polishing","cost_usd":24307.1222,"downtime_hours":8.0752,"me_recovery_pct":-14.6887,"payback_days":8.0934},{"event_date":"2023-01-25","event_type":"dry_dock","cost_usd":1178555.7896,"downtime_hours":587.4156,"me_recovery_pct":96.3028,"payback_days":79.5998},{"event_date":"2023-01-25","event_type":"coating_renewal","cost_usd":1518148.3744,"downtime_hours":0,"me_recovery_pct":96.3028,"payback_days":68.4293},{"event_date":"2023-03-05","event_type":"propeller_polishing","cost_usd":24157.8359,"downtime_hours":7.651,"me_recovery_pct":-177.5901,"payback_days":null},{"event_date":"2023-05-19","event_type":"engine_overhaul","cost_usd":206145.1049,"downtime_hours":183.5495,"me_recovery_pct":-22.062,"payback_days":null},{"event_date":"2024-03-04","event_type":"hull_cleaning","cost_usd":72765.2999,"downtime_hours":25.6707,"me_recovery_pct":96.0336,"payback_days":8.102},{"event_date":"2024-06-04","event_type":"propeller_polishing","cost_usd":34510.691,"downtime_hours":13.1085,"me_recovery_pct":-46.2809,"payback_days":null},{"event_date":"2025-04-16","event_type":"hull_cleaning","cost_usd":64078.7532,"downtime_hours":33.4704,"me_recovery_pct":98.0632,"payback_days":3.4411},{"event_date":"2025-08-25","event_type":"propeller_polishing","cost_usd":18373.2346,"downtime_hours":15.8253,"me_recovery_pct":-24.8151,"payback_days":null},{"event_date":"2026-03-15","event_type":"hull_cleaning","cost_usd":87005.5085,"downtime_hours":21.1097,"me_recovery_pct":92.5746,"payback_days":4.5486},{"event_date":"2026-06-07","event_type":"engine_overhaul","cost_usd":237097.5645,"downtime_hours":215.6888,"me_recovery_pct":-28.941,"payback_days":null}]