[{"inspection_date":"2021-09-18","inspection_type":"diver","hull_fouling_rating":31,"hull_fouling_coverage_pct":41.5888,"propeller_condition":"A","propeller_roughness_um":192.7123,"coating_breakdown_pct":2.2824,"coating_condition":"good","recommended_action":"polish"},{"inspection_date":"2022-04-03","inspection_type":"ROV","hull_fouling_rating":28,"hull_fouling_coverage_pct":37.1379,"propeller_condition":"A","propeller_roughness_um":163.0483,"coating_breakdown_pct":7.9066,"coating_condition":"good","recommended_action":"none"},{"inspection_date":"2022-12-24","inspection_type":"ROV","hull_fouling_rating":14,"hull_fouling_coverage_pct":18.6639,"propeller_condition":"C","propeller_roughness_um":275.4098,"coating_breakdown_pct":18.3661,"coating_condition":"good","recommended_action":"none"},{"inspection_date":"2023-07-04","inspection_type":"UWI","hull_fouling_rating":64,"hull_fouling_coverage_pct":85.0244,"propeller_condition":"A","propeller_roughness_um":206.4453,"coating_breakdown_pct":24.5948,"coating_condition":"fair","recommended_action":"clean"},{"inspection_date":"2024-01-11","inspection_type":"ROV","hull_fouling_rating":9,"hull_fouling_coverage_pct":11.5568,"propeller_condition":"A","propeller_roughness_um":185.4078,"coating_breakdown_pct":1.3166,"coating_condition":"good","recommended_action":"none"},{"inspection_date":"2024-08-09","inspection_type":"diver","hull_fouling_rating":18,"hull_fouling_coverage_pct":23.4167,"propeller_condition":"A","propeller_roughness_um":193.1604,"coating_breakdown_pct":10.4302,"coating_condition":"good","recommended_action":"none"},{"inspection_date":"2025-03-09","inspection_type":"diver","hull_fouling_rating":68,"hull_fouling_coverage_pct":90.5022,"propeller_condition":"C","propeller_roughness_um":287.5945,"coating_breakdown_pct":15.9316,"coating_condition":"good","recommended_action":"clean"},{"inspection_date":"2025-10-10","inspection_type":"ROV","hull_fouling_rating":10,"hull_fouling_coverage_pct":13.1664,"propeller_condition":"B","propeller_roughness_um":236.0373,"coating_breakdown_pct":22.519,"coating_condition":"fair","recommended_action":"none"},{"inspection_date":"2026-04-26","inspection_type":"UWI","hull_fouling_rating":34,"hull_fouling_coverage_pct":44.9584,"propeller_condition":"C","propeller_roughness_um":320.9034,"coating_breakdown_pct":25.5414,"coating_condition":"fair","recommended_action":"polish"}]